odoo/addons/l10n_fr_account_tax_unece/README.rst
odoo/addons/l10n_fr_account_tax_unece/__init__.py
odoo/addons/l10n_fr_account_tax_unece/__manifest__.py
odoo/addons/l10n_fr_account_tax_unece/post_install.py
odoo/addons/l10n_fr_account_tax_unece/i18n/es.po
odoo/addons/l10n_fr_account_tax_unece/i18n/l10n_fr_account_tax_unece.pot
odoo/addons/l10n_fr_account_tax_unece/models/__init__.py
odoo/addons/l10n_fr_account_tax_unece/models/account_chart_template.py
odoo/addons/l10n_fr_account_tax_unece/readme/CONTRIBUTORS.md
odoo/addons/l10n_fr_account_tax_unece/readme/DESCRIPTION.md
odoo/addons/l10n_fr_account_tax_unece/static/description/icon.png
odoo/addons/l10n_fr_account_tax_unece/static/description/index.html
odoo_addon_l10n_fr_account_tax_unece-18.0.1.0.0.3.dist-info/METADATA
odoo_addon_l10n_fr_account_tax_unece-18.0.1.0.0.3.dist-info/WHEEL
odoo_addon_l10n_fr_account_tax_unece-18.0.1.0.0.3.dist-info/top_level.txt
odoo_addon_l10n_fr_account_tax_unece-18.0.1.0.0.3.dist-info/RECORD
